raiwidgets/__init__.py
raiwidgets/__version__.py
raiwidgets/constants.py
raiwidgets/dashboard.py
raiwidgets/error_analysis_constants.py
raiwidgets/error_analysis_dashboard.py
raiwidgets/error_analysis_dashboard_input.py
raiwidgets/error_handling.py
raiwidgets/explanation_constants.py
raiwidgets/explanation_dashboard.py
raiwidgets/explanation_dashboard_input.py
raiwidgets/fairness_dashboard.py
raiwidgets/fairness_metric_calculation.py
raiwidgets/interfaces.py
raiwidgets/model_analysis_dashboard.py
raiwidgets/model_performance_dashboard.py
raiwidgets/responsibleai_dashboard.py
raiwidgets/responsibleai_dashboard_input.py
raiwidgets/widget/3rdpartylicenses.txt
raiwidgets/widget/favicon.ico
raiwidgets/widget/index.html
raiwidgets/widget/main.44959db93b9f59dff9b6.esm.js
raiwidgets/widget/main.44959db93b9f59dff9b6.esm.js.LICENSE.txt
raiwidgets/widget/polyfills.2df2e8ae7005c1bbf442.esm.js
raiwidgets/widget/runtime.28c323bf8ee123f67bad.esm.js
raiwidgets-0.36.0.dist-info/LICENSE
raiwidgets-0.36.0.dist-info/METADATA
raiwidgets-0.36.0.dist-info/WHEEL
raiwidgets-0.36.0.dist-info/top_level.txt
raiwidgets-0.36.0.dist-info/RECORD
